botterino/__init__.py
botterino/__main__.py
botterino/botterino.py
botterino/config.py
botterino/failure.py
botterino/hosterino.py
botterino/posterino.py
botterino/ui.py
botterino/Loader/__init__.py
botterino/Loader/loader.py
botterino/Map/__init__.py
botterino/Map/map.py
botterino/RedditPoller/RedditPoller.py
botterino/RedditPoller/Retry.py
botterino/RedditPoller/__init__.py
botterino/Utils/__init__.py
botterino/Utils/color.py
botterino/Utils/utils.py
botterino-0.5.8.dist-info/LICENSE
botterino-0.5.8.dist-info/METADATA
botterino-0.5.8.dist-info/WHEEL
botterino-0.5.8.dist-info/top_level.txt
botterino-0.5.8.dist-info/RECORD
