Metadata-Version: 2.1
Name: botterino
Version: 0.5.8
Summary: Automate posting and hosting of rounds on /r/picturegame
Home-page: https://github.com/pgitox/botterino
Author: itoxici
Author-email: itox@picturegame.co
Classifier: Programming Language :: Python :: 3
Classifier: License :: OSI Approved :: MIT License
Classifier: Operating System :: OS Independent
Requires-Python: >=3.8
License-File: LICENSE
Requires-Dist: folium
Requires-Dist: praw
Requires-Dist: geopy
Requires-Dist: pyyaml
Requires-Dist: ruamel.yaml
Requires-Dist: sty
Requires-Dist: requests
Requires-Dist: update-checker
Requires-Dist: halo
